CHANGELOG.txt
LICENSE.txt
MANIFEST.in
README.md
setup.py
hbv/__init__.py
hbv/tests.py
hbv_scheduler.egg-info/PKG-INFO
hbv_scheduler.egg-info/SOURCES.txt
hbv_scheduler.egg-info/dependency_links.txt
hbv_scheduler.egg-info/requires.txt
hbv_scheduler.egg-info/top_level.txt