Metadata-Version: 2.1
Name: hbv-scheduler
Version: 0.1.0
Summary: Doctor patient home based visit routing and scheduling algorithm
Home-page: https://github.com/mprashanth54/home-visit-algorithm
Author: Prashanth Mogali
Author-email: m.prashanth54@gmail.com
License: MIT
Platform: UNKNOWN
Classifier: Programming Language :: Python :: 3
Classifier: License :: OSI Approved :: MIT License
Classifier: Operating System :: OS Independent
Requires-Python: >=3.7
